django_richtextfield-1.1.dist-info/DESCRIPTION.rst
django_richtextfield-1.1.dist-info/METADATA
django_richtextfield-1.1.dist-info/metadata.json
django_richtextfield-1.1.dist-info/RECORD
django_richtextfield-1.1.dist-info/top_level.txt
django_richtextfield-1.1.dist-info/WHEEL
djrichtextfield/__init__.py
djrichtextfield/models.py
djrichtextfield/settings.py
djrichtextfield/urls.py
djrichtextfield/views.py
djrichtextfield/widgets.py
djrichtextfield/templates/djrichtextfield/init.js
djrichtextfield/templates/djrichtextfield/init/ckeditor.js
djrichtextfield/templates/djrichtextfield/init/tinymce.js
