Metadata-Version: 2.0
Name: django-richtextfield
Version: 1.1
Summary: A Django model field and widget that renders a customizable WYSIWYG/rich text editor
Home-page: https://github.com/jaap3/django-richtextfield
Author: Jaap Roes
Author-email: jaap.roes@gmail.com
License: MIT
Keywords: django-richtextfield,djrichtextfield django wywiwyg field
Platform: UNKNOWN
Classifier: Development Status :: 5 - Production/Stable
Classifier: Framework :: Django
Classifier: Intended Audience :: Developers
Classifier: License :: OSI Approved :: MIT License
Classifier: Natural Language :: English
Classifier: Programming Language :: Python :: 2
Classifier: Programming Language :: Python :: 2.6
Classifier: Programming Language :: Python :: 2.7
Classifier: Programming Language :: Python :: 3
Classifier: Programming Language :: Python :: 3.3
Classifier: Programming Language :: Python :: 3.4
